tests/__init__.py
tests/test_yao_tool.py
yao_test_package2/__init__.py
yao_test_package2/tools/__init__.py
yao_test_package2/tools/utils.py
yao_test_package2/tools/yao_tool.py
yao_test_package2/yamls/yao_tool.yaml
yao_test_package2-0.0.1.dist-info/METADATA
yao_test_package2-0.0.1.dist-info/WHEEL
yao_test_package2-0.0.1.dist-info/entry_points.txt
yao_test_package2-0.0.1.dist-info/top_level.txt
yao_test_package2-0.0.1.dist-info/RECORD
